Workbook

Sheet Documentation
A1: Molly's Makeup Shop
A3: Author | B3: Marcelo Batista
A4: Date | B4: 45554

Sheet Products
A1: Molly's Makeup Shop
A3: Product ID | B3: Product Type | C3: Product Name | D3: Manufacturer | E3: Product Color | F3: Price
A4: B4579 | B4: Blush | C4: Matte Powder | D4: Glamour Girl | E4: Raspberry | F4: 20
A5: B4580 | B5: Blush | C5: Matte Powder | D5: Glamour Girl | E5: Strawberry Red | F5: 20
A6: B4577 | B6: Blush | C6: Matte Powder | D6: Powder Perfect | E6: Peonie Pink | F6: 15
A7: B4578 | B7: Blush | C7: Matte Powder | D7: Powder Perfect | E7: Sunset Orange | F7: 15
A8: B4579 | B8: Blush | C8: Gel Blush | D8: Bold Beauty | E8: Deep Red | F8: 17
A9: B4580 | B9: Blush | C9: Matte Powder | D9: Bright Eyes | E9: Sunrise | F9: 17
A10: B4581 | B10: Blush | C10: Gel Blush | D10: Fabulous Foundations | E10: Tangerine | F10: 21
A11: B4582 | B11: Blush | C11: Cream Blush | D11: Flirtatious Foundation | E11: Warm Desert | F11: 20
A12: B4583 | B12: Blush | C12: Gel Blush | D12: Hip Highlights | E12: Peach | F12: 18
A13: B4584 | B13: Blush | C13: Cream Blush | D13: Lavish Liners | E13: Apricot Dream | F13: 20
A14: B4585 | B14: Blush | C14: Shimmer Blush | D14: Luminous Lipsticks | E14: Peonie Pink | F14: 16
A15: B4585 | B15: Blush | C15: Gel Blush | D15: Bold Beauty | E15: Raspberry | F15: 16
... A103: M2010 | B103: Mascara | C103: Waterproof Mascara | D103: Hip Highlights | E103: Purple | F103: 19

Sheet Products PivetTable
A3: Count of Price | B3: Column Labels
A4: Row Labels | B4: Bright Eyes | C4: Flirtatious Foundation | D4: Hip Highlights | E4: Luminous Lipsticks | F4: Grand Total
A5: Blush | B5: 1 | C5: 2 | D5: 3 | E5: 1 | F5: 7
A6: Eyeliner | B6: 2 | C6: 1 | D6: 1 | E6: 3 | F6: 7
A7: Grand Total | B7: 3 | C7: 3 | D7: 4 | E7: 4 | F7: 14

Sheet Quarter 1 Employee Sales
A1: Molly's Makeup Shop
A3: Employee ID | B3: First Name | C3: Last Name | D3: Sales Quarter 1
A4: 1001 | B4: Gabby | C4: Cook | D4: 12000
A5: 1002 | B5: Luke | C5: Smith | D5: 13002
A6: 1003 | B6: Sally | C6: Casio | D6: 11156
A7: 1004 | B7: Jon | C7: Wilson | D7: 15098
A8: 1005 | B8: Dean | C8: Angelos | D8: 13874
A9: 1006 | B9: Jackson | C9: Martin | D9: 14287
A10: 1007 | B10: Oliver | C10: Jackson | D10: 15783
A11: 1008 | B11: Mary | C11: Thomas | D11: 10111
A12: 1009 | B12: Faith | C12: Nichols | D12: 12456
D13: =SUM(D4:D12) -> 117767 | E13: TOTAL

Sheet Quarter 2 Employee Sales
A1: Molly's Makeup Shop
A3: Employee ID | B3: First Name | C3: Last Name | D3: Sales Quarter 2
A4: 1001 | B4: Gabby | C4: Cook | D4: 12456
A5: 1002 | B5: Luke | C5: Smith | D5: 15323
A6: 1003 | B6: Sally | C6: Casio | D6: 13421
A7: 1004 | B7: Jon | C7: Wilson | D7: 11009
A8: 1005 | B8: Dean | C8: Angelos | D8: 10234
A9: 1006 | B9: Jackson | C9: Martin | D9: 15098
A10: 1007 | B10: Oliver | C10: Jackson | D10: 12111
A11: 1008 | B11: Mary | C11: Thomas | D11: 10239
A12: 1009 | B12: Faith | C12: Nichols | D12: 9003
D13: =SUM(D4:D12) -> 108894 | E13: TOTAL

Sheet Quarter 3 Employee Sales
A1: Molly's Makeup Shop
A3: Employee ID | B3: First Name | C3: Last Name | D3: Sales Quarter 3
A4: 1001 | B4: Gabby | C4: Cook | D4: 12983
A5: 1002 | B5: Luke | C5: Smith | D5: 10000
A6: 1003 | B6: Sally | C6: Casio | D6: 13984
A7: 1004 | B7: Jon | C7: Wilson | D7: 12876
A8: 1005 | B8: Dean | C8: Angelos | D8: 16543
A9: 1006 | B9: Jackson | C9: Martin | D9: 13574
A10: 1007 | B10: Oliver | C10: Jackson | D10: 10293
A11: 1008 | B11: Mary | C11: Thomas | D11: 9878
A12: 1009 | B12: Faith | C12: Nichols | D12: 10293
D13: =SUM(D4:D12) -> 110424 | E13: TOTAL

Sheet Quarter 4 Employee Sales
A1: Molly's Makeup Shop
A3: Employee ID | B3: First Name | C3: Last Name | D3: Sales Quarter 4
A4: 1001 | B4: Gabby | C4: Cook | D4: 12873
A5: 1002 | B5: Luke | C5: Smith | D5: 13984
A6: 1003 | B6: Sally | C6: Casio | D6: 15872
A7: 1004 | B7: Jon | C7: Wilson | D7: 9883
A8: 1005 | B8: Dean | C8: Angelos | D8: 10847
A9: 1006 | B9: Jackson | C9: Martin | D9: 15982
A10: 1007 | B10: Oliver | C10: Jackson | D10: 14983
A11: 1008 | B11: Mary | C11: Thomas | D11: 13726
A12: 1009 | B12: Faith | C12: Nichols | D12: 11001
D13: =SUM(D4:D12) -> 119151 | E13: TOTAL

Sheet Annual Employee Sales
A1: Molly's Makeup Shop
A3: Employee ID | B3: First Name | C3: Last Name | D3: Annual Sales
A4: 1001 | B4: Gabby | C4: Cook | D4: =SUM('Quarter 1 Employee Sales'!D4+'Quarter 2 Employee Sales'!D4+'Quarter 3 Employee Sales'!D4+'Quarter 4 Employee Sales'!D4) -> 50312
A5: 1002 | B5: Luke | C5: Smith | D5: =SUM('Quarter 1 Employee Sales:Quarter 4 Employee Sales'!D5) -> 52309
A6: 1003 | B6: Sally | C6: Casio | D6: =SUM('Quarter 1 Employee Sales:Quarter 4 Employee Sales'!D6) -> 54433
A7: 1004 | B7: Jon | C7: Wilson | D7: =SUM('Quarter 1 Employee Sales:Quarter 4 Employee Sales'!D7) -> 48866
A8: 1005 | B8: Dean | C8: Angelos | D8: =SUM('Quarter 1 Employee Sales:Quarter 4 Employee Sales'!D8) -> 51498
A9: 1006 | B9: Jackson | C9: Martin | D9: =SUM('Quarter 1 Employee Sales:Quarter 4 Employee Sales'!D9) -> 58941
A10: 1007 | B10: Oliver | C10: Jackson | D10: =SUM('Quarter 1 Employee Sales:Quarter 4 Employee Sales'!D10) -> 53170
A11: 1008 | B11: Mary | C11: Thomas | D11: =SUM('Quarter 1 Employee Sales:Quarter 4 Employee Sales'!D11) -> 43954
A12: 1009 | B12: Faith | C12: Nichols | D12: =SUM('Quarter 1 Employee Sales:Quarter 4 Employee Sales'!D12) -> 42753
D13: =SUM(D4:D12) -> 456236 | E13: TOTAL

Sheet Loan for Location Expansion
A1: Molly's Makeup Shop
A2: Loan to Expand OakBrook Location
A3: Loan | B3: 225000
A4: Rate | B4: 0.08
A5: Years | B5: 15
A6: Payments Per Year | B6: 12
A7: Total Number of Payments | B7: =B5*B6 -> 180
A8: Monthly Payment (PMT) | B8: =-PMT(B4/B6,B7,B3) -> 2150.2172
A9: Total Amount of Payments | B9: =B7*B8 -> 387039.09 | E9: Period: | F9: 1
A10: Cost of Loan | B10: =B9-B3 -> 162039.09
A12: IPMT | B12: =-IPMT(B4/B6,F9,B7,B3) -> 1500
A13: PPMT | B13: =-PPMT(B4/B6,F9,B7,B3) -> 650.21719
A14: PMT = IPMT + PPMT | B14: =B12+B13 -> 2150.2172

Sheet Investment
A1: Molly's Makeup Shop
A3: Start Investment | B3: 1000
A4: Quarterly Contributions | B4: 250
A5: Annual Rate | B5: 0.04
A6: Number of Quarters Contributing | B6: 9
A7: Final Value of Investment (FV) | B7: =FV(B5/4,B6,-B4,-B3) -> 3435.8171
A9: NPER | B9: =NPER(B5/4,-B4,-B3,B7) -> 9
A10: PV | B10: =-PV(B5/4,B6,-B4,B7) -> 1000
A11: Rate | B11: =RATE(B6,-B4,-B3,B7)*4 -> 0.04

Sheet New NorthBrook Store
A1: Molly's Makeup Shop
A2: New Store Opening - NorthBrook
B4: Year 0 - Initial Investment | C4: Return Year 1 | D4: Return Year 2 | E4: Return Year 3 | F4: Return Year 4 | G4: Return Year 5
A5: Annual Return | B5: -750000 | C5: 150000 | D5: 180000 | E5: 250000 | F5: 275000 | G5: 300000
A6: Current Net Return | B6: -750000 | C6: =B6+C5 -> -600000 | D6: =C6+D5 -> -420000 | E6: =D6+E5 -> -170000 | F6: =E6+F5 -> 105000 | G6: =F6+G5 -> 405000
A9: Desired Rate of Return | B9: 0.11
A10: Net Present Value | B10: =NPV(B9,C5:G5)+B5 -> 73211.435
A11: Internal Rate of Return | B11: =IRR(B5:G5) -> 0.14365312
